README.md
setup.py
pylgnetcast/__init__.py
pylgnetcast/__main__.py
pylgnetcast/pylgnetcast.py
pylgnetcast_homeassistant.egg-info/PKG-INFO
pylgnetcast_homeassistant.egg-info/SOURCES.txt
pylgnetcast_homeassistant.egg-info/dependency_links.txt
pylgnetcast_homeassistant.egg-info/not-zip-safe
pylgnetcast_homeassistant.egg-info/top_level.txt