Metadata-Version: 1.0
Name: pylgnetcast-homeassistant
Version: 0.2.0.dev0
Summary: Client for the LG Smart TV running NetCast 3 or 4.
Home-page: https://github.com/wokar/pylgnetcast
Author: UNKNOWN
Author-email: UNKNOWN
License: MIT
Platform: UNKNOWN
